torch_sla/__init__.py
torch_sla/batch_solve.py
torch_sla/distributed.py
torch_sla/io.py
torch_sla/linear_solve.py
torch_sla/nonlinear_solve.py
torch_sla/sparse_tensor.py
torch_sla/backends/__init__.py
torch_sla/backends/pytorch_backend.py
torch_sla/backends/scipy_backend.py
torch_sla-0.1.2.dist-info/licenses/LICENSE
torch_sla-0.1.2.dist-info/METADATA
torch_sla-0.1.2.dist-info/WHEEL
torch_sla-0.1.2.dist-info/top_level.txt
torch_sla-0.1.2.dist-info/RECORD
