Metadata-Version: 2.4
Name: torch-sla
Version: 0.1.2
Summary: PyTorch Sparse Linear Algebra - Differentiable sparse solvers with CUDA support
Home-page: https://github.com/walkerchi/torch-sla
Author: walkerchi
Author-email: walkerchi <walkerchi@example.com>
Maintainer-email: walkerchi <walkerchi@example.com>
License: MIT
Project-URL: Homepage, https://pypi.org/project/torch-sla/
Project-URL: Documentation, https://github.com/walkerchi/torch-sla#readme
Project-URL: Repository, https://github.com/walkerchi/torch-sla
Project-URL: PyPI, https://pypi.org/project/torch-sla/
Project-URL: Issues, https://github.com/walkerchi/torch-sla/issues
Keywords: pytorch,sparse,linear-algebra,cuda,cusolver,cudss,sparse-matrix,linear-solver,differentiable,autograd
Classifier: Development Status :: 4 - Beta
Classifier: Intended Audience :: Developers
Classifier: Intended Audience :: Science/Research
Classifier: License :: OSI Approved :: MIT License
Classifier: Operating System :: OS Independent
Classifier: Programming Language :: Python :: 3
Classifier: Programming Language :: Python :: 3.8
Classifier: Programming Language :: Python :: 3.9
Classifier: Programming Language :: Python :: 3.10
Classifier: Programming Language :: Python :: 3.11
Classifier: Programming Language :: Python :: 3.12
Classifier: Programming Language :: C++
Classifier: Topic :: Scientific/Engineering
Classifier: Topic :: Scientific/Engineering :: Mathematics
Classifier: Topic :: Scientific/Engineering :: Artificial Intelligence
Requires-Python: >=3.8
License-File: LICENSE
Requires-Dist: torch>=1.10.0
Requires-Dist: ninja
Provides-Extra: test
Requires-Dist: pytest>=6.0; extra == "test"
Requires-Dist: numpy>=1.19.0; extra == "test"
Requires-Dist: scipy>=1.5.0; extra == "test"
Provides-Extra: dev
Requires-Dist: pytest>=6.0; extra == "dev"
Requires-Dist: numpy>=1.19.0; extra == "dev"
Requires-Dist: scipy>=1.5.0; extra == "dev"
Requires-Dist: black; extra == "dev"
Requires-Dist: isort; extra == "dev"
Requires-Dist: mypy; extra == "dev"
Requires-Dist: pre-commit; extra == "dev"
Provides-Extra: docs
Requires-Dist: sphinx>=4.0; extra == "docs"
Requires-Dist: furo; extra == "docs"
Requires-Dist: sphinx-autodoc-typehints; extra == "docs"
Provides-Extra: cuda
Requires-Dist: nvidia-cudss-cu12>=0.7.0; extra == "cuda"
Provides-Extra: all
Requires-Dist: pytest>=6.0; extra == "all"
Requires-Dist: numpy>=1.19.0; extra == "all"
Requires-Dist: scipy>=1.5.0; extra == "all"
Requires-Dist: nvidia-cudss-cu12>=0.7.0; extra == "all"
Dynamic: author
Dynamic: home-page
Dynamic: license-file
Dynamic: requires-python
